onfido/__init__.py
onfido/api_client.py
onfido/configuration.py
onfido/exceptions.py
onfido/rest.py
onfido/api/__init__.py
onfido/api/default_api.py
onfido/models/__init__.py
onfido/models/address.py
onfido/models/addresses_list.py
onfido/models/applicant.py
onfido/models/applicants_list.py
onfido/models/check.py
onfido/models/checks_list.py
onfido/models/document.py
onfido/models/documents_list.py
onfido/models/error.py
onfido/models/error_properties.py
onfido/models/id_number.py
onfido/models/live_photo.py
onfido/models/live_photos_list.py
onfido/models/live_video.py
onfido/models/live_videos_list.py
onfido/models/report.py
onfido/models/report_document.py
onfido/models/reports_list.py
onfido/models/sdk_token.py
onfido/models/webhook.py
onfido/models/webhooks_list.py
test/__init__.py
test/test_address.py
test/test_addresses_list.py
test/test_applicant.py
test/test_applicants_list.py
test/test_check.py
test/test_checks_list.py
test/test_default_api.py
test/test_document.py
test/test_documents_list.py
test/test_error.py
test/test_error_properties.py
test/test_id_number.py
test/test_live_photo.py
test/test_live_photos_list.py
test/test_live_video.py
test/test_live_videos_list.py
test/test_report.py
test/test_report_document.py
test/test_reports_list.py
test/test_sdk_token.py
test/test_webhook.py
test/test_webhooks_list.py
onfido-5.0.0.dist-info/LICENSE
onfido-5.0.0.dist-info/METADATA
onfido-5.0.0.dist-info/WHEEL
onfido-5.0.0.dist-info/top_level.txt
onfido-5.0.0.dist-info/RECORD
