Metadata-Version: 1.0
Name: onfido
Version: 5.0.0
Summary: Onfido API
Home-page: UNKNOWN
Author: UNKNOWN
Author-email: UNKNOWN
License: UNKNOWN
Keywords: OpenAPI,OpenAPI-Generator,Onfido API
Platform: UNKNOWN
